LICENSE
MANIFEST.in
README.rst
setup.cfg
setup.py
versioneer.py
terraformspawner/__init__.py
terraformspawner/__main__.py
terraformspawner/_version.py
terraformspawner/cli.py
terraformspawner/terraformspawner.py
terraformspawner.egg-info/PKG-INFO
terraformspawner.egg-info/SOURCES.txt
terraformspawner.egg-info/dependency_links.txt
terraformspawner.egg-info/entry_points.txt
terraformspawner.egg-info/requires.txt
terraformspawner.egg-info/top_level.txt