Metadata-Version: 1.1
Name: terraformspawner
Version: 0.0.2
Summary: Spawn JupyterHub single-user servers with Terraform
Home-page: https://github.com/sodre/terraformspawner
Author: Patrick Sodré
Author-email: sodre@sodre.co
License: UNKNOWN
Keywords: terraformspawner
Platform: UNKNOWN
Classifier: Programming Language :: Python :: 3.6
Classifier: Programming Language :: Python :: 3.7
